print_clear/__init__.py
print_clear/_version.py
print_clear/print_clear.py
print_clear/py.typed
print_clear-2.1.0.dist-info/LICENSE
print_clear-2.1.0.dist-info/METADATA
print_clear-2.1.0.dist-info/WHEEL
print_clear-2.1.0.dist-info/entry_points.txt
print_clear-2.1.0.dist-info/top_level.txt
print_clear-2.1.0.dist-info/RECORD
