Metadata-Version: 2.1
Name: print_clear
Version: 2.1.0
Summary: A tiny CLI used for quoting input lines
License: GPL
Project-URL: Homepage, https://github.com/zwimer/print_clear
Classifier: Programming Language :: Python :: 3
Classifier: Programming Language :: Python :: 3.10
Requires-Python: >=3.10
License-File: LICENSE
Requires-Dist: termcolor
